swch_com/__init__.py
swch_com/factory.py
swch_com/message_types.py
swch_com/node.py
swch_com/peers.py
swch_com/swchagent.py
swch_com-0.2.0.dist-info/METADATA
swch_com-0.2.0.dist-info/WHEEL
swch_com-0.2.0.dist-info/RECORD
