Metadata-Version: 2.3
Name: swch_com
Version: 0.2.0
Summary: A Python package for peer-to-peer communication for swarmchestrate entities
Author: Dr. József Kovács
Author-email: jozsef.kovacs@sztaki.hun-ren.hu
Requires-Python: >=3.12,<4.0
Classifier: Programming Language :: Python :: 3
Classifier: Programming Language :: Python :: 3.12
Classifier: Programming Language :: Python :: 3.13
Requires-Dist: kademlia
Requires-Dist: miniupnpc
Requires-Dist: twisted
